Config/setting.py
jeutil/App.py
jeutil/Async.py
jeutil/ConfigParser.py
jeutil/Env.py
jeutil/Log.py
jeutil/Oss.py
jeutil/Path.py
jeutil/RabbitMQ.py
jeutil/Redis.py
jeutil/Request.py
jeutil/__init__.py
jeutil-1.1.6.dist-info/LICENSE
jeutil-1.1.6.dist-info/METADATA
jeutil-1.1.6.dist-info/WHEEL
jeutil-1.1.6.dist-info/top_level.txt
jeutil-1.1.6.dist-info/RECORD
