Metadata-Version: 2.1
Name: jeutil
Version: 1.1.6
Summary: A simple python libs
Home-page: UNKNOWN
Author: jeanku
Author-email: 
License: UNKNOWN
Keywords: util,libs
Platform: UNKNOWN
Classifier: Programming Language :: Python :: 3
Classifier: License :: OSI Approved :: MIT License
Classifier: Operating System :: OS Independent
Requires-Python: >=3
Requires-Dist: configparser
Requires-Dist: oss2
